CHANGELOG
LICENSE
MANIFEST.in
README.rst
buildout.cfg
setup.cfg
setup.py
tangled.contrib.egg-info/PKG-INFO
tangled.contrib.egg-info/SOURCES.txt
tangled.contrib.egg-info/dependency_links.txt
tangled.contrib.egg-info/entry_points.txt
tangled.contrib.egg-info/requires.txt
tangled.contrib.egg-info/top_level.txt
tangled/contrib/scaffolds/__init__.py
tangled/contrib/scaffolds/core/CHANGELOG
tangled/contrib/scaffolds/core/LICENSE
tangled/contrib/scaffolds/core/MANIFEST.in
tangled/contrib/scaffolds/core/README.rst
tangled/contrib/scaffolds/core/buildout.cfg
tangled/contrib/scaffolds/core/setup.py
tangled/contrib/scaffolds/core/__package__/__init__.py
tangled/contrib/scaffolds/core/__package__/command.py
tangled/contrib/scaffolds/core/__package__/tests/__init__.py
tangled/contrib/scaffolds/core/docs/conf.py
tangled/contrib/scaffolds/default/CHANGELOG
tangled/contrib/scaffolds/default/LICENSE
tangled/contrib/scaffolds/default/MANIFEST.in
tangled/contrib/scaffolds/default/README.rst
tangled/contrib/scaffolds/default/buildout.cfg
tangled/contrib/scaffolds/default/setup.py
tangled/contrib/scaffolds/default/__package__/__init__.py
tangled/contrib/scaffolds/default/__package__/command.py
tangled/contrib/scaffolds/default/__package__/tests/__init__.py
tangled/contrib/scaffolds/default/docs/conf.py
tangled/contrib/tests/__init__.py